odoo8_addon_sql_export-8.0.1.0.0-py2.7-nspkg.pth
odoo_addons/sql_export/__openerp__.py
odoo_addons/sql_export/sql_export.py
odoo_addons/sql_export/__init__.py
odoo_addons/sql_export/sql_export_view.xml
odoo_addons/sql_export/README.rst
odoo_addons/sql_export/security/sql_export_security.xml
odoo_addons/sql_export/security/ir.model.access.csv
odoo_addons/sql_export/i18n/sql_export.pot
odoo_addons/sql_export/i18n/fr.po
odoo_addons/sql_export/wizard/wizard_file_view.xml
odoo_addons/sql_export/wizard/__init__.py
odoo_addons/sql_export/wizard/wizard_file.py
odoo_addons/sql_export/tests/__init__.py
odoo_addons/sql_export/tests/test_sql_query.py
odoo_addons/sql_export/demo/sql_export.xml
odoo_addons/sql_export/static/description/icon.png
odoo8_addon_sql_export-8.0.1.0.0.dist-info/top_level.txt
odoo8_addon_sql_export-8.0.1.0.0.dist-info/WHEEL
odoo8_addon_sql_export-8.0.1.0.0.dist-info/RECORD
odoo8_addon_sql_export-8.0.1.0.0.dist-info/metadata.json
odoo8_addon_sql_export-8.0.1.0.0.dist-info/DESCRIPTION.rst
odoo8_addon_sql_export-8.0.1.0.0.dist-info/METADATA
odoo8_addon_sql_export-8.0.1.0.0.dist-info/namespace_packages.txt
